dcgan_pytorch/__init__.py
dcgan_pytorch/model.py
dcgan_pytorch/utils.py
dcgan_pytorch-0.2.0.dist-info/METADATA
dcgan_pytorch-0.2.0.dist-info/WHEEL
dcgan_pytorch-0.2.0.dist-info/top_level.txt
dcgan_pytorch-0.2.0.dist-info/RECORD
